xray_rpc/app/commander/config_pb2.py
xray_rpc/app/commander/config_pb2_grpc.py
xray_rpc/app/dispatcher/config_pb2.py
xray_rpc/app/dispatcher/config_pb2_grpc.py
xray_rpc/app/dns/config_pb2.py
xray_rpc/app/dns/config_pb2_grpc.py
xray_rpc/app/dns/fakedns/fakedns_pb2.py
xray_rpc/app/dns/fakedns/fakedns_pb2_grpc.py
xray_rpc/app/log/command/config_pb2.py
xray_rpc/app/log/command/config_pb2_grpc.py
xray_rpc/app/log/config_pb2.py
xray_rpc/app/log/config_pb2_grpc.py
xray_rpc/app/observatory/command/command_pb2.py
xray_rpc/app/observatory/command/command_pb2_grpc.py
xray_rpc/app/observatory/config_pb2.py
xray_rpc/app/observatory/config_pb2_grpc.py
xray_rpc/app/policy/config_pb2.py
xray_rpc/app/policy/config_pb2_grpc.py
xray_rpc/app/proxyman/command/command_pb2.py
xray_rpc/app/proxyman/command/command_pb2_grpc.py
xray_rpc/app/proxyman/config_pb2.py
xray_rpc/app/proxyman/config_pb2_grpc.py
xray_rpc/app/reverse/config_pb2.py
xray_rpc/app/reverse/config_pb2_grpc.py
xray_rpc/app/router/command/command_pb2.py
xray_rpc/app/router/command/command_pb2_grpc.py
xray_rpc/app/router/config_pb2.py
xray_rpc/app/router/config_pb2_grpc.py
xray_rpc/app/stats/command/command_pb2.py
xray_rpc/app/stats/command/command_pb2_grpc.py
xray_rpc/app/stats/config_pb2.py
xray_rpc/app/stats/config_pb2_grpc.py
xray_rpc/common/log/log_pb2.py
xray_rpc/common/log/log_pb2_grpc.py
xray_rpc/common/net/address_pb2.py
xray_rpc/common/net/address_pb2_grpc.py
xray_rpc/common/net/destination_pb2.py
xray_rpc/common/net/destination_pb2_grpc.py
xray_rpc/common/net/network_pb2.py
xray_rpc/common/net/network_pb2_grpc.py
xray_rpc/common/net/port_pb2.py
xray_rpc/common/net/port_pb2_grpc.py
xray_rpc/common/protocol/headers_pb2.py
xray_rpc/common/protocol/headers_pb2_grpc.py
xray_rpc/common/protocol/server_spec_pb2.py
xray_rpc/common/protocol/server_spec_pb2_grpc.py
xray_rpc/common/protocol/user_pb2.py
xray_rpc/common/protocol/user_pb2_grpc.py
xray_rpc/common/serial/typed_message_pb2.py
xray_rpc-1.5.2.dist-info/LICENSE
xray_rpc-1.5.2.dist-info/WHEEL
xray_rpc-1.5.2.dist-info/METADATA
xray_rpc-1.5.2.dist-info/RECORD
